client/__init__.py
client/topicland_client.py
client/topicland_cmd.py
server/__init__.py
server/bqplot_graph.py
server/db_service.py
server/graphviz_graph.py
server/import_official_topics.py
server/jaal_graph.py
server/model.py
server/networkx_graph.py
server/networkx_util.py
server/plotly_graph.py
server/pyecharts_graph.py
server/pyvis_graph.py
server/server.py
server/test.py
server/test_db.py
topicland-0.1.0.dist-info/METADATA
topicland-0.1.0.dist-info/WHEEL
topicland-0.1.0.dist-info/entry_points.txt
topicland-0.1.0.dist-info/top_level.txt
topicland-0.1.0.dist-info/RECORD
